setup.py
jamendo/__init__.py
jamendo_api.egg-info/PKG-INFO
jamendo_api.egg-info/SOURCES.txt
jamendo_api.egg-info/dependency_links.txt
jamendo_api.egg-info/not-zip-safe
jamendo_api.egg-info/requires.txt
jamendo_api.egg-info/top_level.txt