Metadata-Version: 1.0
Name: jamendo-api
Version: 0.0.2
Summary: Python Jamendo API library.
Home-page: http://github.com/vincent/python-jamendo
Author: Vincent Lark
Author-email: vincent.lark@gmail.com
License: Redistribution and use in source and binary forms, with or without
